micromigrate/constants.py
micromigrate/finder.py
micromigrate/__init__.py
micromigrate/util.py
micromigrate/types.py
micromigrate/backend_base.py
micromigrate/backend_pysqlite.py
micromigrate/backend_script.py
Micromigrate-0.0.1.dist-info/top_level.txt
Micromigrate-0.0.1.dist-info/METADATA
Micromigrate-0.0.1.dist-info/DESCRIPTION.rst
Micromigrate-0.0.1.dist-info/metadata.json
Micromigrate-0.0.1.dist-info/WHEEL
Micromigrate-0.0.1.dist-info/RECORD
