Metadata-Version: 2.0
Name: Micromigrate
Version: 0.0.1
Summary: Minimal Migration Manager for sqlite
Home-page: UNKNOWN
Author: UNKNOWN
Author-email: UNKNOWN
License: UNKNOWN
Platform: UNKNOWN
